qv_ollama_sdk/__init__.py
qv_ollama_sdk/client.py
qv_ollama_sdk/domain/__init__.py
qv_ollama_sdk/domain/models.py
qv_ollama_sdk/services/__init__.py
qv_ollama_sdk/services/ollama_conversation_service.py
qv_ollama_sdk-0.9.1.dist-info/licenses/LICENSE
qv_ollama_sdk-0.9.1.dist-info/METADATA
qv_ollama_sdk-0.9.1.dist-info/WHEEL
qv_ollama_sdk-0.9.1.dist-info/top_level.txt
qv_ollama_sdk-0.9.1.dist-info/RECORD
