Metadata-Version: 2.4
Name: qv-ollama-sdk
Version: 0.9.1
Summary: A simple SDK for interacting with the Ollama API by automatically creating a conversation (chat history)
Author-email: Thomas Bernhard <thomas@quantyverse.com>
License: MIT
Project-URL: Homepage, https://github.com/quantyverse/qv-ollama-sdk
Project-URL: Bug Tracker, https://github.com/quantyverse/qv-ollama-sdk/issues
Project-URL: Documentation, https://github.com/quantyverse/qv-ollama-sdk#readme
Keywords: ollama,llm,ai,chat,sdk,domain-driven-design
Classifier: Development Status :: 4 - Beta
Classifier: Intended Audience :: Developers
Classifier: License :: OSI Approved :: MIT License
Classifier: Programming Language :: Python :: 3
Classifier: Programming Language :: Python :: 3.12
Classifier: Topic :: Software Development :: Libraries :: Python Modules
Classifier: Topic :: Scientific/Engineering :: Artificial Intelligence
Requires-Python: >=3.10
License-File: LICENSE
Requires-Dist: ollama>=0.5.0
Requires-Dist: pytest>=8.3.4
Provides-Extra: dev
Requires-Dist: pytest>=7.4.0; extra == "dev"
Dynamic: license-file
